HISTORY.rst
MANIFEST.in
NOTICE.rst
setup.py
doc/LICENSE
doc/README.rst
shadow_server_api/__init__.py
shadow_server_api/api.py
shadow_server_api.egg-info/PKG-INFO
shadow_server_api.egg-info/SOURCES.txt
shadow_server_api.egg-info/dependency_links.txt
shadow_server_api.egg-info/requires.txt
shadow_server_api.egg-info/top_level.txt