Metadata-Version: 1.0
Name: shadow-server-api
Version: 1.0.4
Summary: Shadow Server - Binary Whitelist and MD5/SHA1 AV Service API
Home-page: https://github.com/blacktop/team-cymru-api
Author: blacktop
Author-email: dev@blacktop.io
License: GPLv3
Platform: UNKNOWN
